seawave_spectrum/__init__.py
seawave_spectrum/config.toml
seawave_spectrum/core.py
seawave_spectrum/decorators.py
seawave_spectrum/dispersion.py
seawave_spectrum/integrate.py
seawave_spectrum/twoscaledmodel.py
seawave_spectrum-1.1.4.dist-info/LICENSE
seawave_spectrum-1.1.4.dist-info/METADATA
seawave_spectrum-1.1.4.dist-info/WHEEL
seawave_spectrum-1.1.4.dist-info/top_level.txt
seawave_spectrum-1.1.4.dist-info/RECORD
