Metadata-Version: 2.1
Name: seawave-spectrum
Version: 1.1.4
Summary: UNKNOWN
Home-page: https://github.com/kannab98/seawave-spectrum
Author: Kirill Ponur
Author-email: ponur@ipfran.ru
License: UNKNOWN
Platform: UNKNOWN
Classifier: Programming Language :: Python :: 3
Classifier: License :: OSI Approved :: GNU General Public License v3 (GPLv3)
Classifier: Operating System :: OS Independent
Requires-Python: >=3.6
License-File: LICENSE
Requires-Dist: numpy
Requires-Dist: scipy
Requires-Dist: toml
